mongoSimultan/__init__.py
mongoSimultan/base_types.py
mongoSimultan/component.py
mongoSimultan/fields.py
yumm-0.0.1.dist-info/LICENSE.txt
yumm-0.0.1.dist-info/METADATA
yumm-0.0.1.dist-info/WHEEL
yumm-0.0.1.dist-info/entry_points.txt
yumm-0.0.1.dist-info/top_level.txt
yumm-0.0.1.dist-info/RECORD
